odoo/addons/stock_picking_procure_method/README.rst
odoo/addons/stock_picking_procure_method/__init__.py
odoo/addons/stock_picking_procure_method/__manifest__.py
odoo/addons/stock_picking_procure_method/i18n/stock_picking_procure_method.pot
odoo/addons/stock_picking_procure_method/models/__init__.py
odoo/addons/stock_picking_procure_method/models/stock_picking.py
odoo/addons/stock_picking_procure_method/readme/CONFIGURE.rst
odoo/addons/stock_picking_procure_method/readme/CONTRIBUTORS.rst
odoo/addons/stock_picking_procure_method/readme/DESCRIPTION.rst
odoo/addons/stock_picking_procure_method/readme/INSTALL.rst
odoo/addons/stock_picking_procure_method/readme/USAGE.rst
odoo/addons/stock_picking_procure_method/static/description/icon.png
odoo/addons/stock_picking_procure_method/static/description/index.html
odoo/addons/stock_picking_procure_method/tests/__init__.py
odoo/addons/stock_picking_procure_method/tests/test_stock_picking_procure_method.py
odoo/addons/stock_picking_procure_method/views/stock_picking_views.xml
odoo11_addon_stock_picking_procure_method-11.0.1.0.0.99.dev5.dist-info/METADATA
odoo11_addon_stock_picking_procure_method-11.0.1.0.0.99.dev5.dist-info/WHEEL
odoo11_addon_stock_picking_procure_method-11.0.1.0.0.99.dev5.dist-info/top_level.txt
odoo11_addon_stock_picking_procure_method-11.0.1.0.0.99.dev5.dist-info/RECORD
